weathergen/.DS_Store
weathergen/__init__.py
weathergen/generator.npy
weathergen-1.0.1.dist-info/LICENSE
weathergen-1.0.1.dist-info/METADATA
weathergen-1.0.1.dist-info/WHEEL
weathergen-1.0.1.dist-info/top_level.txt
weathergen-1.0.1.dist-info/RECORD
